pyEngine2D_ddd/__init__.py
pyEngine2D_ddd/exceptions.py
pyEngine2D_ddd/game_loop.py
pyEngine2D_ddd/game_object.py
pyEngine2D_ddd/screen_init.py
pyEngine2D_ddd/data/null.png
pyEngine2D_ddd/scripts/Collider2D.py
pyEngine2D_ddd/scripts/__init__.py
pyEngine2D_ddd/scripts/transform.py
user/__init__.py
user/player_movement.py
pyEngine2D_ddd-1.0.1.dist-info/License.txt
pyEngine2D_ddd-1.0.1.dist-info/METADATA
pyEngine2D_ddd-1.0.1.dist-info/WHEEL
pyEngine2D_ddd-1.0.1.dist-info/top_level.txt
pyEngine2D_ddd-1.0.1.dist-info/RECORD
