Metadata-Version: 2.1
Name: pyEngine2D-ddd
Version: 1.0.1
Summary: UNKNOWN
Home-page: UNKNOWN
Author: ddd Makbema
Author-email: dddmakbema@gmail.com
License: MIT
Platform: UNKNOWN
Classifier: Programming Language :: Python :: 3
Classifier: License :: OSI Approved :: MIT License
Classifier: Operating System :: OS Independent
Requires-Dist: pygame
